ep_amendment_extract/__init__.py
ep_amendment_extract/am_labeler.py
ep_amendment_extract/diff.py
ep_amendment_extract/dossier_retriever.py
ep_amendment_extract/meps.py
ep_amendment_extract/parser.py
europarl_amendment_extract-1.1.1.dist-info/METADATA
europarl_amendment_extract-1.1.1.dist-info/WHEEL
europarl_amendment_extract-1.1.1.dist-info/top_level.txt
europarl_amendment_extract-1.1.1.dist-info/RECORD
