Metadata-Version: 2.1
Name: europarl-amendment-extract
Version: 1.1.1
Summary: Extract amendments from European Parliament docx files
Author: Sebastien Campion
License: MIT
Requires-Dist: beautifulsoup4 ==4.12.2
Requires-Dist: ipython ==8.13.2
Requires-Dist: pip-chill ==1.0.3
Requires-Dist: python-docx ==0.8.11
Requires-Dist: xmltodict ==0.13.0
Requires-Dist: requests ==2.31.0
Requires-Dist: jsondiff ==2.0.0
Requires-Dist: python-levenshtein ==0.21.0
Requires-Dist: tqdm ==4.65.0
